lm_scorer/__init__.py
lm_scorer/bin/__init__.py
lm_scorer/bin/cli.py
lm_scorer/models/__init__.py
lm_scorer/models/abc/__init__.py
lm_scorer/models/abc/base.py
lm_scorer/models/abc/batch.py
lm_scorer/models/abc/transformers.py
lm_scorer/models/auto.py
lm_scorer/models/gpt2.py
lm_scorer_hashformers-0.4.2.dist-info/entry_points.txt
lm_scorer_hashformers-0.4.2.dist-info/LICENSE
lm_scorer_hashformers-0.4.2.dist-info/WHEEL
lm_scorer_hashformers-0.4.2.dist-info/METADATA
lm_scorer_hashformers-0.4.2.dist-info/RECORD
