Metadata-Version: 2.1
Name: lm-scorer-hashformers
Version: 0.4.2
Summary: Language Model based sentences scoring library
Home-page: https://github.com/simonepri/lm-scorer#readme
License: MIT
Keywords: language,model,lm,probability,score
Author: Simone Primarosa
Author-email: simonepri@outlook.com
Requires-Python: >=3.6,<3.8
Classifier: License :: OSI Approved :: MIT License
Classifier: Programming Language :: Python :: 3
Classifier: Programming Language :: Python :: 3.6
Classifier: Programming Language :: Python :: 3.7
Requires-Dist: pip (>=20.0.0)
Requires-Dist: torch (>=1.4.0)
Requires-Dist: transformers (>=2.9.0)
Project-URL: Repository, https://github.com/simonepri/lm-scorer
